pyoxide-0.4.1.dist-info/METADATA
pyoxide-0.4.1.dist-info/WHEEL
oxide/__init__.py
oxide/oxide.cp39-win_amd64.pyd
pyoxide-0.4.1.dist-info/RECORD
