Metadata-Version: 2.1
Name: pyoxide
Version: 0.4.1
Classifier: Programming Language :: Rust
Classifier: Programming Language :: Python :: Implementation :: CPython
Classifier: Programming Language :: Python :: Implementation :: PyPy
Summary: Mixing Python with Rust
Author: Todd Young
Author-email: todd.young@pinnaclereliability.com
Maintainer-email: Todd Young <todd.young@pinnaclereliability.com>
Requires-Python: >=3.8
